Pokemila/__init__.py
Pokemila/pokemon.csv
Pokemila/random_pokemon.py
Pokemila-1.0.1.dist-info/METADATA
Pokemila-1.0.1.dist-info/WHEEL
Pokemila-1.0.1.dist-info/top_level.txt
Pokemila-1.0.1.dist-info/RECORD
